confidence_planner/__init__.py
confidence_planner/confidence_planner.py
confidence_planner-0.1.3.dist-info/LICENSE
confidence_planner-0.1.3.dist-info/METADATA
confidence_planner-0.1.3.dist-info/WHEEL
confidence_planner-0.1.3.dist-info/top_level.txt
confidence_planner-0.1.3.dist-info/RECORD
