Metadata-Version: 2.1
Name: confidence-planner
Version: 0.1.3
Summary: A Python library for estimating confidence intervals around accuracy and sample sizes for classification experiments.
Home-page: https://github.com/dabrze/confidence-planner
Author: Antoni Klorek, Karol Roszak, Dariusz Brzezinski
Author-email: dariusz.brzezinski@cs.put.poznan.pl
Classifier: Programming Language :: Python :: 3
Classifier: License :: OSI Approved :: MIT License
Classifier: Operating System :: OS Independent
Classifier: Topic :: Software Development
Classifier: Topic :: Scientific/Engineering
Classifier: Programming Language :: Python :: 3.7
Classifier: Programming Language :: Python :: 3.8
Classifier: Programming Language :: Python :: 3.9
Requires-Python: >=3.7
License-File: LICENSE
Requires-Dist: numpy (>=1.21.0)
Requires-Dist: scipy (>=1.7.1)
Requires-Dist: statsmodels (>=0.12.1matplotlib)
